[
  {
    "start": "02:30",
    "stop": "03:00",
    "channel": "AsianetPlus.in",
    "channelId": "AsianetPlus.in",
    "channelName": "Asianet Plus",
    "startTs": 1776393000000,
    "stopTs": 1776394800000,
    "title": "Devi Mahathmyam",
    "desc": "An anthology of stories which deal with the legends and myths related to Goddess Durga. S01 E805."
  },
  {
    "start": "03:00",
    "stop": "03:30",
    "channel": "AsianetPlus.in",
    "channelId": "AsianetPlus.in",
    "channelName": "Asianet Plus",
    "startTs": 1776394800000,
    "stopTs": 1776396600000,
    "title": "Malikappuram",
    "desc": "Lord Ayyappan takes the form of a school student to help Unnimol overcome obstacles. S01 E57."
  },
  {
    "start": "03:30",
    "stop": "06:30",
    "channel": "AsianetPlus.in",
    "channelId": "AsianetPlus.in",
    "channelName": "Asianet Plus",
    "startTs": 1776396600000,
    "stopTs": 1776407400000,
    "title": "Kudumbasametham",
    "desc": "Sivan faces many challenges as his father is against Sivan&apos;s wish of becoming a singer."
  },
  {
    "start": "06:30",
    "stop": "09:30",
    "channel": "AsianetPlus.in",
    "channelId": "AsianetPlus.in",
    "channelName": "Asianet Plus",
    "startTs": 1776407400000,
    "stopTs": 1776418200000,
    "title": "Oru Muthassi Katha",
    "desc": "The fishermen are in trouble when a stranger with ulterior motives visits their village."
  },
  {
    "start": "09:30",
    "stop": "12:00",
    "channel": "AsianetPlus.in",
    "channelId": "AsianetPlus.in",
    "channelName": "Asianet Plus",
    "startTs": 1776418200000,
    "stopTs": 1776427200000,
    "title": "Rani Padmini",
    "desc": "Rani and Padmini embark on an unfamiliar journey while getting to know each other."
  },
  {
    "start": "12:00",
    "stop": "12:30",
    "channel": "AsianetPlus.in",
    "channelId": "AsianetPlus.in",
    "channelName": "Asianet Plus",
    "startTs": 1776427200000,
    "stopTs": 1776429000000,
    "title": "Thoovalsparsham",
    "desc": "Pavithra disrupts Avinash&apos;s scheme to secure financial help from his parents. S01 E226."
  },
  {
    "start": "12:30",
    "stop": "13:00",
    "channel": "AsianetPlus.in",
    "channelId": "AsianetPlus.in",
    "channelName": "Asianet Plus",
    "startTs": 1776429000000,
    "stopTs": 1776430800000,
    "title": "Malikappuram",
    "desc": "Lord Ayyappan takes the form of a school student to help Unnimol overcome obstacles. S01 E58."
  },
  {
    "start": "13:00",
    "stop": "13:30",
    "channel": "AsianetPlus.in",
    "channelId": "AsianetPlus.in",
    "channelName": "Asianet Plus",
    "startTs": 1776430800000,
    "stopTs": 1776432600000,
    "title": "Eatho Janma Kalpanayil",
    "desc": "Love blooms between Sruthy, a cheerful girl and Ashwin, an arrogant wealthy businessman. S01 E228."
  },
  {
    "start": "13:30",
    "stop": "14:00",
    "channel": "AsianetPlus.in",
    "channelId": "AsianetPlus.in",
    "channelName": "Asianet Plus",
    "startTs": 1776432600000,
    "stopTs": 1776434400000,
    "title": "Chandrikayil Aliyunnu Chandrakantham",
    "desc": "Gautham, an IPS officer, is forced to marry Alakananda, an aspiring doctor. S01 E230."
  },
  {
    "start": "14:00",
    "stop": "14:30",
    "channel": "AsianetPlus.in",
    "channelId": "AsianetPlus.in",
    "channelName": "Asianet Plus",
    "startTs": 1776434400000,
    "stopTs": 1776436200000,
    "title": "Chirikkum Thalika",
    "desc": "A compilation of various entertaining comedy scenes from various Malayalam movies."
  },
  {
    "start": "14:30",
    "stop": "15:00",
    "channel": "AsianetPlus.in",
    "channelId": "AsianetPlus.in",
    "channelName": "Asianet Plus",
    "startTs": 1776436200000,
    "stopTs": 1776438000000,
    "title": "Paadatha Painkili",
    "desc": "A young woman faces endless hardships as she searches for happiness and love. S01 E229."
  },
  {
    "start": "15:00",
    "stop": "15:30",
    "channel": "AsianetPlus.in",
    "channelId": "AsianetPlus.in",
    "channelName": "Asianet Plus",
    "startTs": 1776438000000,
    "stopTs": 1776439800000,
    "title": "Devi Mahathmyam",
    "desc": "An anthology of stories which deal with the legends and myths related to Goddess Durga. S01 E806."
  },
  {
    "start": "15:30",
    "stop": "16:00",
    "channel": "AsianetPlus.in",
    "channelId": "AsianetPlus.in",
    "channelName": "Asianet Plus",
    "startTs": 1776439800000,
    "stopTs": 1776441600000,
    "title": "Santhwanam",
    "desc": "Sridevi&apos;s happy and united family faces adversities that challenge their bonding. S01 E151."
  },
  {
    "start": "16:00",
    "stop": "16:30",
    "channel": "AsianetPlus.in",
    "channelId": "AsianetPlus.in",
    "channelName": "Asianet Plus",
    "startTs": 1776441600000,
    "stopTs": 1776443400000,
    "title": "Mounaragam",
    "desc": "The life of Kalyani, who is speech impaired, takes a turn after she meets Kiran. S01 E1668."
  },
  {
    "start": "16:30",
    "stop": "17:00",
    "channel": "AsianetPlus.in",
    "channelId": "AsianetPlus.in",
    "channelName": "Asianet Plus",
    "startTs": 1776443400000,
    "stopTs": 1776445200000,
    "title": "Geetha Govindam",
    "desc": "A middle-aged businessman&apos;s past affects his romantic relationship with a younger girl. S01 E116."
  },
  {
    "start": "17:00",
    "stop": "17:30",
    "channel": "AsianetPlus.in",
    "channelId": "AsianetPlus.in",
    "channelName": "Asianet Plus",
    "startTs": 1776445200000,
    "stopTs": 1776447000000,
    "title": "Nammal",
    "desc": "Sreedaran manipulates Gayathri to destroy her sympathy for Jeevan. S01 E168."
  },
  {
    "start": "17:30",
    "stop": "18:00",
    "channel": "AsianetPlus.in",
    "channelId": "AsianetPlus.in",
    "channelName": "Asianet Plus",
    "startTs": 1776447000000,
    "stopTs": 1776448800000,
    "title": "Chirikkum Thalika",
    "desc": "A compilation of various entertaining comedy scenes from various Malayalam movies."
  },
  {
    "start": "18:00",
    "stop": "21:00",
    "channel": "AsianetPlus.in",
    "channelId": "AsianetPlus.in",
    "channelName": "Asianet Plus",
    "startTs": 1776448800000,
    "stopTs": 1776459600000,
    "title": "Ennu Ninte Moideen",
    "desc": "Moideen and Kanchanamala fight against an orthodox society for their undying love."
  },
  {
    "start": "21:00",
    "stop": "21:30",
    "channel": "AsianetPlus.in",
    "channelId": "AsianetPlus.in",
    "channelName": "Asianet Plus",
    "startTs": 1776459600000,
    "stopTs": 1776461400000,
    "title": "Chirikkum Thalika",
    "desc": "A compilation of various entertaining comedy scenes from various Malayalam movies. S02 E130."
  },
  {
    "start": "21:30",
    "stop": "22:00",
    "channel": "AsianetPlus.in",
    "channelId": "AsianetPlus.in",
    "channelName": "Asianet Plus",
    "startTs": 1776461400000,
    "stopTs": 1776463200000,
    "title": "Chirikkum Thalika",
    "desc": "A compilation of various entertaining comedy scenes from various Malayalam movies. S02 E131."
  },
  {
    "start": "22:00",
    "stop": "00:00",
    "channel": "AsianetPlus.in",
    "channelId": "AsianetPlus.in",
    "channelName": "Asianet Plus",
    "startTs": 1776463200000,
    "stopTs": 1776470400000,
    "title": "Udayam Padinjaru",
    "desc": "Lakshmi and Menon&apos;s married life is shattered when Lakshmi discovers Menon&apos;s affair."
  },
  {
    "start": "00:00",
    "stop": "02:30",
    "channel": "AsianetPlus.in",
    "channelId": "AsianetPlus.in",
    "channelName": "Asianet Plus",
    "startTs": 1776470400000,
    "stopTs": 1776479400000,
    "title": "Movie",
    "desc": "Bringing the best in television."
  },
  {
    "start": "00:30",
    "stop": "03:30",
    "channel": "AsianetPlus.in",
    "channelId": "AsianetPlus.in",
    "channelName": "Asianet Plus",
    "startTs": 1776472200000,
    "stopTs": 1776483000000,
    "title": "Movie",
    "desc": "The movie name is yet to be announced by the channel."
  },
  {
    "start": "02:30",
    "stop": "03:00",
    "channel": "AsianetPlus.in",
    "channelId": "AsianetPlus.in",
    "channelName": "Asianet Plus",
    "startTs": 1776479400000,
    "stopTs": 1776481200000,
    "title": "Europe Malayalee Journal",
    "desc": "A portrayal of the lives and challenges faced by expatriates from Kerala living in Europe."
  },
  {
    "start": "03:00",
    "stop": "03:30",
    "channel": "AsianetPlus.in",
    "channelId": "AsianetPlus.in",
    "channelName": "Asianet Plus",
    "startTs": 1776481200000,
    "stopTs": 1776483000000,
    "title": "Soorya Festival",
    "desc": "Artists perform in an annual arts festival that showcases Indian culture."
  },
  {
    "start": "03:30",
    "stop": "06:30",
    "channel": "AsianetPlus.in",
    "channelId": "AsianetPlus.in",
    "channelName": "Asianet Plus",
    "startTs": 1776483000000,
    "stopTs": 1776493800000,
    "title": "Movie",
    "desc": "Bringing the best in television."
  },
  {
    "start": "06:30",
    "stop": "09:30",
    "channel": "AsianetPlus.in",
    "channelId": "AsianetPlus.in",
    "channelName": "Asianet Plus",
    "startTs": 1776493800000,
    "stopTs": 1776504600000,
    "title": "Movie",
    "desc": "Bringing the best in television."
  },
  {
    "start": "09:30",
    "stop": "10:00",
    "channel": "AsianetPlus.in",
    "channelId": "AsianetPlus.in",
    "channelName": "Asianet Plus",
    "startTs": 1776504600000,
    "stopTs": 1776506400000,
    "title": "Asthamakkum Alarjikkum St.Paul Pharma",
    "desc": "The host presents some holistic Ayurvedic medicines to effectively treat Asthma and allergies."
  },
  {
    "start": "10:00",
    "stop": "10:30",
    "channel": "AsianetPlus.in",
    "channelId": "AsianetPlus.in",
    "channelName": "Asianet Plus",
    "startTs": 1776506400000,
    "stopTs": 1776508200000,
    "title": "Chirikkum Thalika",
    "desc": "A compilation of various entertaining comedy scenes from various Malayalam movies."
  },
  {
    "start": "10:30",
    "stop": "11:00",
    "channel": "AsianetPlus.in",
    "channelId": "AsianetPlus.in",
    "channelName": "Asianet Plus",
    "startTs": 1776508200000,
    "stopTs": 1776510000000,
    "title": "Chirikkum Thalika",
    "desc": "A compilation of various entertaining comedy scenes from various Malayalam movies."
  },
  {
    "start": "11:00",
    "stop": "11:15",
    "channel": "AsianetPlus.in",
    "channelId": "AsianetPlus.in",
    "channelName": "Asianet Plus",
    "startTs": 1776510000000,
    "stopTs": 1776510900000,
    "title": "Chirikkum Thalika",
    "desc": "A compilation of various entertaining comedy scenes from various Malayalam movies."
  },
  {
    "start": "11:15",
    "stop": "13:45",
    "channel": "AsianetPlus.in",
    "channelId": "AsianetPlus.in",
    "channelName": "Asianet Plus",
    "startTs": 1776510900000,
    "stopTs": 1776519900000,
    "title": "Hero Indian Super League",
    "desc": "Professional football teams vie for the prestigious trophy in the Indian Super League."
  },
  {
    "start": "12:30",
    "stop": "15:30",
    "channel": "AsianetPlus.in",
    "channelId": "AsianetPlus.in",
    "channelName": "Asianet Plus",
    "startTs": 1776515400000,
    "stopTs": 1776526200000,
    "title": "Movie",
    "desc": "The movie name is yet to be announced by the channel."
  },
  {
    "start": "13:45",
    "stop": "16:15",
    "channel": "AsianetPlus.in",
    "channelId": "AsianetPlus.in",
    "channelName": "Asianet Plus",
    "startTs": 1776519900000,
    "stopTs": 1776528900000,
    "title": "Indian Super League Soccer",
    "desc": "Professional football teams vie for the prestigious trophy in the Indian Super League."
  },
  {
    "start": "15:30",
    "stop": "19:00",
    "channel": "AsianetPlus.in",
    "channelId": "AsianetPlus.in",
    "channelName": "Asianet Plus",
    "startTs": 1776526200000,
    "stopTs": 1776538800000,
    "title": "Movie",
    "desc": "The movie name is yet to be announced by the channel."
  },
  {
    "start": "16:15",
    "stop": "19:30",
    "channel": "AsianetPlus.in",
    "channelId": "AsianetPlus.in",
    "channelName": "Asianet Plus",
    "startTs": 1776528900000,
    "stopTs": 1776540600000,
    "title": "Movie",
    "desc": "Bringing the best in television."
  },
  {
    "start": "19:00",
    "stop": "21:30",
    "channel": "AsianetPlus.in",
    "channelId": "AsianetPlus.in",
    "channelName": "Asianet Plus",
    "startTs": 1776538800000,
    "stopTs": 1776547800000,
    "title": "Movie",
    "desc": "The movie name is yet to be announced by the channel."
  },
  {
    "start": "21:30",
    "stop": "00:00",
    "channel": "AsianetPlus.in",
    "channelId": "AsianetPlus.in",
    "channelName": "Asianet Plus",
    "startTs": 1776547800000,
    "stopTs": 1776556800000,
    "title": "Movie",
    "desc": "The movie name is yet to be announced by the channel."
  },
  {
    "start": "00:00",
    "stop": "02:30",
    "channel": "AsianetPlus.in",
    "channelId": "AsianetPlus.in",
    "channelName": "Asianet Plus",
    "startTs": 1776556800000,
    "stopTs": 1776565800000,
    "title": "Movie",
    "desc": "The movie name is yet to be announced by the channel."
  },
  {
    "start": "02:30",
    "stop": "03:00",
    "channel": "AsianetPlus.in",
    "channelId": "AsianetPlus.in",
    "channelName": "Asianet Plus",
    "startTs": 1776565800000,
    "stopTs": 1776567600000,
    "title": "Devi Mahaathmyam",
    "desc": "King Sudarshan escapes his foes and finds refuge in an ashram, where he encounters a saint who shares inspiring stories of the Goddess, leading to profound revelations."
  },
  {
    "start": "03:00",
    "stop": "03:30",
    "channel": "AsianetPlus.in",
    "channelId": "AsianetPlus.in",
    "channelName": "Asianet Plus",
    "startTs": 1776567600000,
    "stopTs": 1776569400000,
    "title": "Devi Mahaathmyam",
    "desc": "King Sudarshan escapes his foes and finds refuge in an ashram, where he encounters a saint who shares inspiring stories of the Goddess, leading to profound revelations."
  }
]