[
  {
    "start": "01:30",
    "stop": "03:00",
    "channel": "MazhavilManorama.in",
    "channelId": "MazhavilManorama.in",
    "channelName": "Mazhavil Manorama HD",
    "startTs": 1776562200000,
    "stopTs": 1776567600000,
    "title": "Oru Chiri Iru Chiri Bumper Chiri",
    "desc": "Skilled participants take the stage to perform various comedy skits to win prizes. S01 E79."
  },
  {
    "start": "03:00",
    "stop": "04:30",
    "channel": "MazhavilManorama.in",
    "channelId": "MazhavilManorama.in",
    "channelName": "Mazhavil Manorama HD",
    "startTs": 1776567600000,
    "stopTs": 1776573000000,
    "title": "Oru Chiri Iru Chiri Bumper Chiri",
    "desc": "Skilled participants take the stage to perform various comedy skits to win prizes. S01 E76."
  },
  {
    "start": "04:30",
    "stop": "05:30",
    "channel": "MazhavilManorama.in",
    "channelId": "MazhavilManorama.in",
    "channelName": "Mazhavil Manorama HD",
    "startTs": 1776573000000,
    "stopTs": 1776576600000,
    "title": "Oru Chiri Iru Chiri Bumper Chiri",
    "desc": "Skilled participants take the stage to perform various comedy skits to win prizes. S01 E77."
  },
  {
    "start": "05:30",
    "stop": "06:00",
    "channel": "MazhavilManorama.in",
    "channelId": "MazhavilManorama.in",
    "channelName": "Mazhavil Manorama HD",
    "startTs": 1776576600000,
    "stopTs": 1776578400000,
    "title": "Marimayam",
    "desc": "A host of interesting characters encounter comical situations at government institutions. S01 E944."
  },
  {
    "start": "06:00",
    "stop": "08:45",
    "channel": "MazhavilManorama.in",
    "channelId": "MazhavilManorama.in",
    "channelName": "Mazhavil Manorama HD",
    "startTs": 1776578400000,
    "stopTs": 1776588300000,
    "title": "Azadi",
    "desc": "A husband plans to free his wife and newborn baby after she becomes a suspect of a murder."
  },
  {
    "start": "08:45",
    "stop": "11:48",
    "channel": "MazhavilManorama.in",
    "channelId": "MazhavilManorama.in",
    "channelName": "Mazhavil Manorama HD",
    "startTs": 1776588300000,
    "stopTs": 1776599280000,
    "title": "Shikkari Shambhu",
    "desc": "When word spreads of a rogue tiger on the loose, an entire village turn to Peeli for help."
  },
  {
    "start": "11:48",
    "stop": "15:00",
    "channel": "MazhavilManorama.in",
    "channelId": "MazhavilManorama.in",
    "channelName": "Mazhavil Manorama HD",
    "startTs": 1776599280000,
    "stopTs": 1776610800000,
    "title": "Jomonte Suvisheshangal",
    "desc": "Jomon mends his ways and becomes more responsible after a failed business venture."
  },
  {
    "start": "15:00",
    "stop": "15:30",
    "channel": "MazhavilManorama.in",
    "channelId": "MazhavilManorama.in",
    "channelName": "Mazhavil Manorama HD",
    "startTs": 1776610800000,
    "stopTs": 1776612600000,
    "title": "Marimayam",
    "desc": "A host of interesting characters encounter comical situations at government institutions. S01 E946."
  },
  {
    "start": "15:30",
    "stop": "16:30",
    "channel": "MazhavilManorama.in",
    "channelId": "MazhavilManorama.in",
    "channelName": "Mazhavil Manorama HD",
    "startTs": 1776612600000,
    "stopTs": 1776616200000,
    "title": "Oru Chiri Iru Chiri Bumper Chiri",
    "desc": "Skilled participants take the stage to perform various comedy skits to win prizes. S01 E79."
  },
  {
    "start": "16:30",
    "stop": "17:00",
    "channel": "MazhavilManorama.in",
    "channelId": "MazhavilManorama.in",
    "channelName": "Mazhavil Manorama HD",
    "startTs": 1776616200000,
    "stopTs": 1776618000000,
    "title": "Elevate",
    "desc": "An investment mobilization reality show offer funding, mentoring, incubation and networking support for innovative, high-growth-potential startups, guiding them on the path to success. S02 E04."
  },
  {
    "start": "17:00",
    "stop": "17:30",
    "channel": "MazhavilManorama.in",
    "channelId": "MazhavilManorama.in",
    "channelName": "Mazhavil Manorama HD",
    "startTs": 1776618000000,
    "stopTs": 1776619800000,
    "title": "Marimayam",
    "desc": "A host of interesting characters encounter comical situations at government institutions. S01 E946."
  },
  {
    "start": "17:30",
    "stop": "18:30",
    "channel": "MazhavilManorama.in",
    "channelId": "MazhavilManorama.in",
    "channelName": "Mazhavil Manorama HD",
    "startTs": 1776619800000,
    "stopTs": 1776623400000,
    "title": "Oru Chiri Iru Chiri Bumper Chiri",
    "desc": "Skilled participants take the stage to perform various comedy skits to win prizes. S01 E74."
  },
  {
    "start": "18:30",
    "stop": "18:52",
    "channel": "MazhavilManorama.in",
    "channelId": "MazhavilManorama.in",
    "channelName": "Mazhavil Manorama HD",
    "startTs": 1776623400000,
    "stopTs": 1776624720000,
    "title": "Oru Chiri Iru Chiri Bumper Chiri",
    "desc": "Skilled participants take the stage to perform various comedy skits to win prizes. S01 E727."
  },
  {
    "start": "18:52",
    "stop": "19:44",
    "channel": "MazhavilManorama.in",
    "channelId": "MazhavilManorama.in",
    "channelName": "Mazhavil Manorama HD",
    "startTs": 1776624720000,
    "stopTs": 1776627840000,
    "title": "Oru Chiri Iru Chiri Bumper Chiri",
    "desc": "Skilled participants take the stage to perform various comedy skits to win prizes. S01 E77."
  },
  {
    "start": "19:44",
    "stop": "20:06",
    "channel": "MazhavilManorama.in",
    "channelId": "MazhavilManorama.in",
    "channelName": "Mazhavil Manorama HD",
    "startTs": 1776627840000,
    "stopTs": 1776629160000,
    "title": "Marimayam",
    "desc": "A host of interesting characters encounter comical situations at government institutions. S01 E944."
  },
  {
    "start": "20:06",
    "stop": "21:12",
    "channel": "MazhavilManorama.in",
    "channelId": "MazhavilManorama.in",
    "channelName": "Mazhavil Manorama HD",
    "startTs": 1776629160000,
    "stopTs": 1776633120000,
    "title": "Oru Chiri Iru Chiri Bumper Chiri",
    "desc": "Skilled participants take the stage to perform various comedy skits to win prizes. S01 E74."
  },
  {
    "start": "21:12",
    "stop": "22:18",
    "channel": "MazhavilManorama.in",
    "channelId": "MazhavilManorama.in",
    "channelName": "Mazhavil Manorama HD",
    "startTs": 1776633120000,
    "stopTs": 1776637080000,
    "title": "Oru Chiri Iru Chiri Bumper Chiri",
    "desc": "Skilled participants take the stage to perform various comedy skits to win prizes. S01 E81."
  },
  {
    "start": "22:18",
    "stop": "23:24",
    "channel": "MazhavilManorama.in",
    "channelId": "MazhavilManorama.in",
    "channelName": "Mazhavil Manorama HD",
    "startTs": 1776637080000,
    "stopTs": 1776641040000,
    "title": "Oru Chiri Iru Chiri Bumper Chiri",
    "desc": "Skilled participants take the stage to perform various comedy skits to win prizes. S01 E76."
  },
  {
    "start": "23:24",
    "stop": "23:46",
    "channel": "MazhavilManorama.in",
    "channelId": "MazhavilManorama.in",
    "channelName": "Mazhavil Manorama HD",
    "startTs": 1776641040000,
    "stopTs": 1776642360000,
    "title": "Marimayam",
    "desc": "A host of interesting characters encounter comical situations at government institutions. S01 E946."
  },
  {
    "start": "23:46",
    "stop": "00:30",
    "channel": "MazhavilManorama.in",
    "channelId": "MazhavilManorama.in",
    "channelName": "Mazhavil Manorama HD",
    "startTs": 1776642360000,
    "stopTs": 1776645000000,
    "title": "Oru Chiri Iru Chiri Bumper Chiri",
    "desc": "Skilled participants take the stage to perform various comedy skits to win prizes. S01 E79."
  },
  {
    "start": "00:30",
    "stop": "01:00",
    "channel": "MazhavilManorama.in",
    "channelId": "MazhavilManorama.in",
    "channelName": "Mazhavil Manorama HD",
    "startTs": 1776645000000,
    "stopTs": 1776646800000,
    "title": "Ruchi Vismayam",
    "desc": "Culinary experts share recipes for various dishes from different cuisines. S01 E26."
  },
  {
    "start": "01:00",
    "stop": "01:30",
    "channel": "MazhavilManorama.in",
    "channelId": "MazhavilManorama.in",
    "channelName": "Mazhavil Manorama HD",
    "startTs": 1776646800000,
    "stopTs": 1776648600000,
    "title": "Oru Chiri Iru Chiri Bumper Chiri",
    "desc": "Skilled participants take the stage to perform various comedy skits to win prizes. S01 E726."
  },
  {
    "start": "01:30",
    "stop": "02:30",
    "channel": "MazhavilManorama.in",
    "channelId": "MazhavilManorama.in",
    "channelName": "Mazhavil Manorama HD",
    "startTs": 1776648600000,
    "stopTs": 1776652200000,
    "title": "Oru Chiri Iru Chiri Bumper Chiri",
    "desc": "Skilled participants take the stage to perform various comedy skits to win prizes. S01 E78."
  },
  {
    "start": "02:30",
    "stop": "03:00",
    "channel": "MazhavilManorama.in",
    "channelId": "MazhavilManorama.in",
    "channelName": "Mazhavil Manorama HD",
    "startTs": 1776652200000,
    "stopTs": 1776654000000,
    "title": "Marimayam",
    "desc": "A host of interesting characters encounter comical situations at government institutions. S01 E945."
  },
  {
    "start": "03:00",
    "stop": "03:30",
    "channel": "MazhavilManorama.in",
    "channelId": "MazhavilManorama.in",
    "channelName": "Mazhavil Manorama HD",
    "startTs": 1776654000000,
    "stopTs": 1776655800000,
    "title": "Unni Kannan",
    "desc": "Unnikannan descends to Earth to fight evil and restore humanity with peace and happiness. S01 E30."
  },
  {
    "start": "03:30",
    "stop": "04:00",
    "channel": "MazhavilManorama.in",
    "channelId": "MazhavilManorama.in",
    "channelName": "Mazhavil Manorama HD",
    "startTs": 1776655800000,
    "stopTs": 1776657600000,
    "title": "Darmmayodhavu Garudan",
    "desc": "Garuda must obey his cruel snake captors to set his beloved mother free. S01 E59."
  },
  {
    "start": "04:00",
    "stop": "04:30",
    "channel": "MazhavilManorama.in",
    "channelId": "MazhavilManorama.in",
    "channelName": "Mazhavil Manorama HD",
    "startTs": 1776657600000,
    "stopTs": 1776659400000,
    "title": "Super Kanmani",
    "desc": "Rejected by most of her community due to a birth defect, Kanmani pursues her aspirations. S01 E477."
  },
  {
    "start": "04:30",
    "stop": "05:00",
    "channel": "MazhavilManorama.in",
    "channelId": "MazhavilManorama.in",
    "channelName": "Mazhavil Manorama HD",
    "startTs": 1776659400000,
    "stopTs": 1776661200000,
    "title": "Ottashikharam",
    "desc": "A childless couple opt for surrogacy but soon complexities arise. S01 E226."
  },
  {
    "start": "05:00",
    "stop": "05:30",
    "channel": "MazhavilManorama.in",
    "channelId": "MazhavilManorama.in",
    "channelName": "Mazhavil Manorama HD",
    "startTs": 1776661200000,
    "stopTs": 1776663000000,
    "title": "Archana Chechi L L B",
    "desc": "Guardian to her brothers, a lawyer faces new challenges when her ex-husband remarries. S01 E310."
  },
  {
    "start": "05:30",
    "stop": "06:00",
    "channel": "MazhavilManorama.in",
    "channelId": "MazhavilManorama.in",
    "channelName": "Mazhavil Manorama HD",
    "startTs": 1776663000000,
    "stopTs": 1776664800000,
    "title": "Othiri Othiri Swapnangal",
    "desc": "Varsha, an ambitious young woman, strives to overcome personal struggles and societal stigma while Shivananda, a fearless journalist, fights against corruption and deep family secrets. S01 E138."
  },
  {
    "start": "06:00",
    "stop": "06:30",
    "channel": "MazhavilManorama.in",
    "channelId": "MazhavilManorama.in",
    "channelName": "Mazhavil Manorama HD",
    "startTs": 1776664800000,
    "stopTs": 1776666600000,
    "title": "Oru Chiri Iru Chiri Bumper Chiri",
    "desc": "Skilled participants take the stage to perform various comedy skits to win prizes. S01 E727."
  },
  {
    "start": "06:30",
    "stop": "09:41",
    "channel": "MazhavilManorama.in",
    "channelId": "MazhavilManorama.in",
    "channelName": "Mazhavil Manorama HD",
    "startTs": 1776666600000,
    "stopTs": 1776678060000,
    "title": "Thozha",
    "desc": "An ex-convict becomes a caretaker to a millionaire who is a quadriplegic."
  },
  {
    "start": "09:41",
    "stop": "12:30",
    "channel": "MazhavilManorama.in",
    "channelId": "MazhavilManorama.in",
    "channelName": "Mazhavil Manorama HD",
    "startTs": 1776678060000,
    "stopTs": 1776688200000,
    "title": "Aparichithan",
    "desc": "Three mischievous college girls have a spooky encounter with a mysterious wildlife photographer."
  },
  {
    "start": "12:30",
    "stop": "13:00",
    "channel": "MazhavilManorama.in",
    "channelId": "MazhavilManorama.in",
    "channelName": "Mazhavil Manorama HD",
    "startTs": 1776688200000,
    "stopTs": 1776690000000,
    "title": "Darmmayodhavu Garudan",
    "desc": "Garuda must obey his cruel snake captors to set his beloved mother free. S01 E60."
  },
  {
    "start": "13:00",
    "stop": "13:30",
    "channel": "MazhavilManorama.in",
    "channelId": "MazhavilManorama.in",
    "channelName": "Mazhavil Manorama HD",
    "startTs": 1776690000000,
    "stopTs": 1776691800000,
    "title": "Archana Chechi L L B",
    "desc": "Guardian to her brothers, a lawyer faces new challenges when her ex-husband remarries. S01 E311."
  },
  {
    "start": "13:30",
    "stop": "14:00",
    "channel": "MazhavilManorama.in",
    "channelId": "MazhavilManorama.in",
    "channelName": "Mazhavil Manorama HD",
    "startTs": 1776691800000,
    "stopTs": 1776693600000,
    "title": "Othiri Othiri Swapnangal",
    "desc": "Varsha, an ambitious young woman, strives to overcome personal struggles and societal stigma while Shivananda, a fearless journalist, fights against corruption and deep family secrets. S01 E139."
  },
  {
    "start": "14:00",
    "stop": "14:30",
    "channel": "MazhavilManorama.in",
    "channelId": "MazhavilManorama.in",
    "channelName": "Mazhavil Manorama HD",
    "startTs": 1776693600000,
    "stopTs": 1776695400000,
    "title": "Ottashikharam",
    "desc": "A childless couple opt for surrogacy but soon complexities arise. S01 E227."
  },
  {
    "start": "14:30",
    "stop": "15:00",
    "channel": "MazhavilManorama.in",
    "channelId": "MazhavilManorama.in",
    "channelName": "Mazhavil Manorama HD",
    "startTs": 1776695400000,
    "stopTs": 1776697200000,
    "title": "Super Kanmani",
    "desc": "Rejected by most of her community due to a birth defect, Kanmani pursues her aspirations. S01 E478."
  },
  {
    "start": "15:00",
    "stop": "16:30",
    "channel": "MazhavilManorama.in",
    "channelId": "MazhavilManorama.in",
    "channelName": "Mazhavil Manorama HD",
    "startTs": 1776697200000,
    "stopTs": 1776702600000,
    "title": "Oru Chiri Iru Chiri Bumper Chiri",
    "desc": "Skilled participants take the stage to perform various comedy skits to win prizes. S01 E83."
  },
  {
    "start": "16:30",
    "stop": "18:00",
    "channel": "MazhavilManorama.in",
    "channelId": "MazhavilManorama.in",
    "channelName": "Mazhavil Manorama HD",
    "startTs": 1776702600000,
    "stopTs": 1776708000000,
    "title": "Oru Chiri Iru Chiri Bumper Chiri",
    "desc": "Skilled participants take the stage to perform various comedy skits to win prizes. S01 E83."
  },
  {
    "start": "18:00",
    "stop": "18:30",
    "channel": "MazhavilManorama.in",
    "channelId": "MazhavilManorama.in",
    "channelName": "Mazhavil Manorama HD",
    "startTs": 1776708000000,
    "stopTs": 1776709800000,
    "title": "Oru Chiri Iru Chiri Bumper Chiri",
    "desc": "Skilled participants take the stage to perform various comedy skits to win prizes. S01 E727."
  },
  {
    "start": "18:30",
    "stop": "18:52",
    "channel": "MazhavilManorama.in",
    "channelId": "MazhavilManorama.in",
    "channelName": "Mazhavil Manorama",
    "startTs": 1776709800000,
    "stopTs": 1776711120000,
    "title": "Oru Chiri Iru Chiri Bumper Chiri Special",
    "desc": "A Malayalam comedy reality show where contestants perform skits and stand-up comedy to entertain judges and win prizes."
  },
  {
    "start": "18:52",
    "stop": "19:18",
    "channel": "MazhavilManorama.in",
    "channelId": "MazhavilManorama.in",
    "channelName": "Mazhavil Manorama",
    "startTs": 1776711120000,
    "stopTs": 1776712680000,
    "title": "Othiri Othiri Swapnangal",
    "desc": "Varsha, a Wayanad disaster survivor, escapes to Kochi to find her missing father and rebuild her life while being hunted by her cruel step father Raghavan and Chandradas, who wants to marry her."
  },
  {
    "start": "19:18",
    "stop": "19:44",
    "channel": "MazhavilManorama.in",
    "channelId": "MazhavilManorama.in",
    "channelName": "Mazhavil Manorama",
    "startTs": 1776712680000,
    "stopTs": 1776714240000,
    "title": "Archana Chechi L L B",
    "desc": "Follow Archana Chechi as she shares life lessons, personal stories, and heartfelt advice, inspiring viewers with warmth and wisdom."
  },
  {
    "start": "19:44",
    "stop": "20:06",
    "channel": "MazhavilManorama.in",
    "channelId": "MazhavilManorama.in",
    "channelName": "Mazhavil Manorama",
    "startTs": 1776714240000,
    "stopTs": 1776715560000,
    "title": "Darmmayodhavu Garudan",
    "desc": "An intense mythological drama where Garudan stands as a symbol of justice, battling powerful enemies while protecting the innocent and restoring faith through courage and sacrifice."
  },
  {
    "start": "20:06",
    "stop": "20:28",
    "channel": "MazhavilManorama.in",
    "channelId": "MazhavilManorama.in",
    "channelName": "Mazhavil Manorama",
    "startTs": 1776715560000,
    "stopTs": 1776716880000,
    "title": "Super Kanmani",
    "desc": "Super Kanmani follows Abhishek as he supports his mother through challenges."
  },
  {
    "start": "20:28",
    "stop": "20:50",
    "channel": "MazhavilManorama.in",
    "channelId": "MazhavilManorama.in",
    "channelName": "Mazhavil Manorama",
    "startTs": 1776716880000,
    "stopTs": 1776718200000,
    "title": "Ottashikharam",
    "desc": "Kala is forced to marry her brother-in-law when her sister can&apos;t conceive. What follows is a tale of emotional conflict, sacrifice, and tradition versus personal happiness."
  },
  {
    "start": "20:50",
    "stop": "21:12",
    "channel": "MazhavilManorama.in",
    "channelId": "MazhavilManorama.in",
    "channelName": "Mazhavil Manorama",
    "startTs": 1776718200000,
    "stopTs": 1776719520000,
    "title": "Othiri Othiri Swapnangal",
    "desc": "Varsha, a Wayanad disaster survivor, escapes to Kochi to find her missing father and rebuild her life while being hunted by her cruel step father Raghavan and Chandradas, who wants to marry her."
  },
  {
    "start": "21:12",
    "stop": "22:18",
    "channel": "MazhavilManorama.in",
    "channelId": "MazhavilManorama.in",
    "channelName": "Mazhavil Manorama",
    "startTs": 1776719520000,
    "stopTs": 1776723480000,
    "title": "Oru Chiri Iru Chiri Bumper Chiri",
    "desc": "A Malayalam comedy reality show where contestants perform skits and stand-up comedy to entertain judges and win prizes."
  },
  {
    "start": "22:18",
    "stop": "22:40",
    "channel": "MazhavilManorama.in",
    "channelId": "MazhavilManorama.in",
    "channelName": "Mazhavil Manorama",
    "startTs": 1776723480000,
    "stopTs": 1776724800000,
    "title": "Darmmayodhavu Garudan",
    "desc": "An intense mythological drama where Garudan stands as a symbol of justice, battling powerful enemies while protecting the innocent and restoring faith through courage and sacrifice."
  },
  {
    "start": "22:40",
    "stop": "23:02",
    "channel": "MazhavilManorama.in",
    "channelId": "MazhavilManorama.in",
    "channelName": "Mazhavil Manorama",
    "startTs": 1776724800000,
    "stopTs": 1776726120000,
    "title": "Super Kanmani",
    "desc": "Super Kanmani follows Abhishek as he supports his mother through challenges."
  },
  {
    "start": "23:02",
    "stop": "23:24",
    "channel": "MazhavilManorama.in",
    "channelId": "MazhavilManorama.in",
    "channelName": "Mazhavil Manorama",
    "startTs": 1776726120000,
    "stopTs": 1776727440000,
    "title": "Ottashikharam",
    "desc": "Kala is forced to marry her brother-in-law when her sister can&apos;t conceive. What follows is a tale of emotional conflict, sacrifice, and tradition versus personal happiness."
  },
  {
    "start": "23:24",
    "stop": "00:30",
    "channel": "MazhavilManorama.in",
    "channelId": "MazhavilManorama.in",
    "channelName": "Mazhavil Manorama",
    "startTs": 1776727440000,
    "stopTs": 1776731400000,
    "title": "Oru Chiri Iru Chiri Bumper Chiri",
    "desc": "A Malayalam comedy reality show where contestants perform skits and stand-up comedy to entertain judges and win prizes."
  },
  {
    "start": "00:30",
    "stop": "01:00",
    "channel": "MazhavilManorama.in",
    "channelId": "MazhavilManorama.in",
    "channelName": "Mazhavil Manorama",
    "startTs": 1776731400000,
    "stopTs": 1776733200000,
    "title": "Ruchi Vismayam",
    "desc": "Ruchi Vismayam is a weekday food show with great recipes, chefs, and more."
  },
  {
    "start": "01:00",
    "stop": "01:30",
    "channel": "MazhavilManorama.in",
    "channelId": "MazhavilManorama.in",
    "channelName": "Mazhavil Manorama",
    "startTs": 1776733200000,
    "stopTs": 1776735000000,
    "title": "Oru Chiri Iru Chiri Bumper Chiri Special",
    "desc": "A Malayalam comedy reality show where contestants perform skits and stand-up comedy to entertain judges and win prizes."
  },
  {
    "start": "01:30",
    "stop": "02:30",
    "channel": "MazhavilManorama.in",
    "channelId": "MazhavilManorama.in",
    "channelName": "Mazhavil Manorama",
    "startTs": 1776735000000,
    "stopTs": 1776738600000,
    "title": "Oru Chiri Iru Chiri Bumper Chiri",
    "desc": "A Malayalam comedy reality show where contestants perform skits and stand-up comedy to entertain judges and win prizes."
  },
  {
    "start": "02:30",
    "stop": "03:00",
    "channel": "MazhavilManorama.in",
    "channelId": "MazhavilManorama.in",
    "channelName": "Mazhavil Manorama",
    "startTs": 1776738600000,
    "stopTs": 1776740400000,
    "title": "Marimayam",
    "desc": "Marimayam, a sitcom on Mazhavil Manorama, portrays actual public incidents."
  },
  {
    "start": "03:00",
    "stop": "03:30",
    "channel": "MazhavilManorama.in",
    "channelId": "MazhavilManorama.in",
    "channelName": "Mazhavil Manorama",
    "startTs": 1776740400000,
    "stopTs": 1776742200000,
    "title": "Unni Kannan",
    "desc": "A principled Village Officer and his assertive lawyer wife navigate daily social and family issues, humorously balancing traditional values with modern thinking in marriage."
  }
]