[
  {
    "start": "00:30",
    "stop": "03:30",
    "channel": "StarGoldRomance.in",
    "channelId": "StarGoldRomance.in",
    "channelName": "STAR GOLD ROMANCE",
    "startTs": 1776126600000,
    "stopTs": 1776137400000,
    "title": "Movie",
    "desc": "Bringing the best in television."
  },
  {
    "start": "01:45",
    "stop": "04:42",
    "channel": "StarGoldRomance.in",
    "channelId": "StarGoldRomance.in",
    "channelName": "Star Gold Romance",
    "startTs": 1776131100000,
    "stopTs": 1776141720000,
    "title": "Bunty Aur Babli 2",
    "desc": "Retired con couple Bunty and Babli return to the game to stop a young duo using their signature style to rob people."
  },
  {
    "start": "03:30",
    "stop": "06:30",
    "channel": "StarGoldRomance.in",
    "channelId": "StarGoldRomance.in",
    "channelName": "STAR GOLD ROMANCE",
    "startTs": 1776137400000,
    "stopTs": 1776148200000,
    "title": "Movie",
    "desc": "Bringing the best in television."
  },
  {
    "start": "04:42",
    "stop": "07:45",
    "channel": "StarGoldRomance.in",
    "channelId": "StarGoldRomance.in",
    "channelName": "Star Gold Romance",
    "startTs": 1776141720000,
    "stopTs": 1776152700000,
    "title": "Benaam Badsha",
    "desc": "Abandoned as a baby, Deepak, a young man turns to crime until he meets Jyoti."
  },
  {
    "start": "06:30",
    "stop": "09:30",
    "channel": "StarGoldRomance.in",
    "channelId": "StarGoldRomance.in",
    "channelName": "STAR GOLD ROMANCE",
    "startTs": 1776148200000,
    "stopTs": 1776159000000,
    "title": "Movie",
    "desc": "Bringing the best in television."
  },
  {
    "start": "07:45",
    "stop": "11:00",
    "channel": "StarGoldRomance.in",
    "channelId": "StarGoldRomance.in",
    "channelName": "Star Gold Romance",
    "startTs": 1776152700000,
    "stopTs": 1776164400000,
    "title": "Aaina",
    "desc": "Roma returns and seeks Ravi&apos;s hand."
  },
  {
    "start": "09:30",
    "stop": "12:30",
    "channel": "StarGoldRomance.in",
    "channelId": "StarGoldRomance.in",
    "channelName": "STAR GOLD ROMANCE",
    "startTs": 1776159000000,
    "stopTs": 1776169800000,
    "title": "Movie",
    "desc": "Bringing the best in television."
  },
  {
    "start": "11:00",
    "stop": "14:25",
    "channel": "StarGoldRomance.in",
    "channelId": "StarGoldRomance.in",
    "channelName": "Star Gold Romance",
    "startTs": 1776164400000,
    "stopTs": 1776176700000,
    "title": "Mujhse Shaadi Karogi",
    "desc": "In Goa, roommates Sunny and Sameer are rivals for Rani&apos;s heart. Sameer must confront his past mistakes and Sunny&apos;s determination to win her over. Love gets complicated!"
  },
  {
    "start": "12:30",
    "stop": "15:30",
    "channel": "StarGoldRomance.in",
    "channelId": "StarGoldRomance.in",
    "channelName": "STAR GOLD ROMANCE",
    "startTs": 1776169800000,
    "stopTs": 1776180600000,
    "title": "Movie",
    "desc": "Bringing the best in television."
  },
  {
    "start": "14:25",
    "stop": "17:05",
    "channel": "StarGoldRomance.in",
    "channelId": "StarGoldRomance.in",
    "channelName": "Star Gold Romance",
    "startTs": 1776176700000,
    "stopTs": 1776186300000,
    "title": "Humko Tumse Pyaar Hai",
    "desc": "A blind girl loses her lover just when she regains her sight and meets another man who falls in love with her. She accepts his proposal, but around the same time, her former lover returns."
  },
  {
    "start": "15:30",
    "stop": "20:30",
    "channel": "StarGoldRomance.in",
    "channelId": "StarGoldRomance.in",
    "channelName": "STAR GOLD ROMANCE",
    "startTs": 1776180600000,
    "stopTs": 1776198600000,
    "title": "Movie",
    "desc": "Bringing the best in television."
  },
  {
    "start": "17:05",
    "stop": "19:38",
    "channel": "StarGoldRomance.in",
    "channelId": "StarGoldRomance.in",
    "channelName": "Star Gold Romance",
    "startTs": 1776186300000,
    "stopTs": 1776195480000,
    "title": "Hello Brother",
    "desc": "An officer&apos;s life is saved by a heart-transplant and he finds himself being guided by the spirit of his donor. The donor worked for a drug courier Co."
  },
  {
    "start": "19:38",
    "stop": "21:56",
    "channel": "StarGoldRomance.in",
    "channelId": "StarGoldRomance.in",
    "channelName": "Star Gold Romance",
    "startTs": 1776195480000,
    "stopTs": 1776203760000,
    "title": "Badmaash Company",
    "desc": "In the &apos;90s, four friends start a company which turns out to be an instant hit due to the unorthodox methods employed."
  },
  {
    "start": "19:50",
    "stop": "22:26",
    "channel": "StarGoldRomance.in",
    "channelId": "StarGoldRomance.in",
    "channelName": "Star Gold Romance",
    "startTs": 1776196200000,
    "stopTs": 1776205560000,
    "title": "Movie",
    "desc": "Bringing the best in television."
  },
  {
    "start": "21:56",
    "stop": "22:51",
    "channel": "StarGoldRomance.in",
    "channelId": "StarGoldRomance.in",
    "channelName": "Star Gold Romance",
    "startTs": 1776203760000,
    "stopTs": 1776207060000,
    "title": "Bal Ganesh 3",
    "desc": "Follow the charming and mischievous tales of young Lord Ganesha as he embarks on magical adventures, teaching valuable lessons of courage, kindness, and wisdom through fun-filled divine escapades."
  },
  {
    "start": "22:26",
    "stop": "22:51",
    "channel": "StarGoldRomance.in",
    "channelId": "StarGoldRomance.in",
    "channelName": "Star Gold Romance",
    "startTs": 1776205560000,
    "stopTs": 1776207060000,
    "title": "Fillers",
    "desc": "A comprehensive compilation of promotional videos and trailers of Bollywood movies featuring popular actors is played sequentially."
  },
  {
    "start": "22:51",
    "stop": "01:17",
    "channel": "StarGoldRomance.in",
    "channelId": "StarGoldRomance.in",
    "channelName": "Star Gold Romance",
    "startTs": 1776207060000,
    "stopTs": 1776215820000,
    "title": "Movie",
    "desc": "The movie name is yet to be announced by the channel."
  },
  {
    "start": "01:17",
    "stop": "04:03",
    "channel": "StarGoldRomance.in",
    "channelId": "StarGoldRomance.in",
    "channelName": "Star Gold Romance",
    "startTs": 1776215820000,
    "stopTs": 1776225780000,
    "title": "Movie",
    "desc": "The movie name is yet to be announced by the channel."
  },
  {
    "start": "04:03",
    "stop": "07:35",
    "channel": "StarGoldRomance.in",
    "channelId": "StarGoldRomance.in",
    "channelName": "Star Gold Romance",
    "startTs": 1776225780000,
    "stopTs": 1776238500000,
    "title": "Movie",
    "desc": "The movie name is yet to be announced by the channel."
  },
  {
    "start": "07:35",
    "stop": "10:58",
    "channel": "StarGoldRomance.in",
    "channelId": "StarGoldRomance.in",
    "channelName": "Star Gold Romance",
    "startTs": 1776238500000,
    "stopTs": 1776250680000,
    "title": "Movie",
    "desc": "The movie name is yet to be announced by the channel."
  },
  {
    "start": "10:58",
    "stop": "14:25",
    "channel": "StarGoldRomance.in",
    "channelId": "StarGoldRomance.in",
    "channelName": "Star Gold Romance",
    "startTs": 1776250680000,
    "stopTs": 1776263100000,
    "title": "Movie",
    "desc": "The movie name is yet to be announced by the channel."
  },
  {
    "start": "14:25",
    "stop": "18:05",
    "channel": "StarGoldRomance.in",
    "channelId": "StarGoldRomance.in",
    "channelName": "Star Gold Romance",
    "startTs": 1776263100000,
    "stopTs": 1776276300000,
    "title": "Movie",
    "desc": "The movie name is yet to be announced by the channel."
  },
  {
    "start": "18:05",
    "stop": "19:59",
    "channel": "StarGoldRomance.in",
    "channelId": "StarGoldRomance.in",
    "channelName": "Star Gold Romance",
    "startTs": 1776276300000,
    "stopTs": 1776283140000,
    "title": "Movie",
    "desc": "The movie name is yet to be announced by the channel."
  },
  {
    "start": "19:59",
    "stop": "22:27",
    "channel": "StarGoldRomance.in",
    "channelId": "StarGoldRomance.in",
    "channelName": "Star Gold Romance",
    "startTs": 1776283140000,
    "stopTs": 1776292020000,
    "title": "Movie",
    "desc": "The movie name is yet to be announced by the channel."
  },
  {
    "start": "22:27",
    "stop": "22:50",
    "channel": "StarGoldRomance.in",
    "channelId": "StarGoldRomance.in",
    "channelName": "Star Gold Romance",
    "startTs": 1776292020000,
    "stopTs": 1776293400000,
    "title": "Fillers",
    "desc": "Catch nonstop entertainment with back-to-back promos, music, and fun fillers from your favorite movies and shows. Perfect for binge-watching and keeping the excitement alive!"
  },
  {
    "start": "22:50",
    "stop": "00:59",
    "channel": "StarGoldRomance.in",
    "channelId": "StarGoldRomance.in",
    "channelName": "Star Gold Romance",
    "startTs": 1776293400000,
    "stopTs": 1776301140000,
    "title": "Movie",
    "desc": "The movie name is yet to be announced by the channel."
  },
  {
    "start": "00:59",
    "stop": "03:44",
    "channel": "StarGoldRomance.in",
    "channelId": "StarGoldRomance.in",
    "channelName": "Star Gold Romance",
    "startTs": 1776301140000,
    "stopTs": 1776311040000,
    "title": "Movie",
    "desc": "The movie name is yet to be announced by the channel."
  }
]